Metadata-Version: 2.4
Name: mseep-mcp-oi-wiki
Version: 0.1.1
Summary: Add your description here
Author-email: mseep <support@skydeck.ai>
Requires-Python: >=3.13
Requires-Dist: fastembed>=0.6.1
Requires-Dist: mcp[cli]>=1.6.0
Requires-Dist: openai>=1.76.0
Requires-Dist: pymilvus>=2.5.7
Requires-Dist: transformers>=4.51.3
